setup.py
combine_package.egg-info/PKG-INFO
combine_package.egg-info/SOURCES.txt
combine_package.egg-info/dependency_links.txt
combine_package.egg-info/top_level.txt
dyc_package_new/main.py
dyc_package_new/person.py
dyc_package_new/test.py
yuan_cheng_package_new/person.py
yuan_cheng_package_new/test.py
yuan_cheng_package_new/yuancheng.py