Metadata-Version: 2.1
Name: combine-package
Version: 1.0.0.1
Summary: Description of your package
Author: dyc
Author-email: your@email.com
